botrun_litellm/__init__.py
botrun_litellm/botrun_litellm.py
botrun_litellm/utils/__init__.py
botrun_litellm/utils/llm_utils.py
botrun_litellm-0.2.6.dist-info/METADATA
botrun_litellm-0.2.6.dist-info/WHEEL
botrun_litellm-0.2.6.dist-info/RECORD
