Metadata-Version: 2.3
Name: botrun_litellm
Version: 0.2.6
Summary: A wrapper for litellm with TAIDE configuration support
Author: sebastian-hsu
Author-email: sebastian.hsu@gmail.com
Requires-Python: >=3.11
Classifier: Programming Language :: Python :: 3
Classifier: Programming Language :: Python :: 3.11
Classifier: Programming Language :: Python :: 3.12
Classifier: Programming Language :: Python :: 3.13
Requires-Dist: litellm (>=1.55.4)
Requires-Dist: python-dotenv
